gmlp_flax/__init__.py
gmlp_flax/layers.py
gmlp_flax/model.py
gmlp_flax/utils.py
gmlp_flax-0.0.1.dist-info/LICENSE
gmlp_flax-0.0.1.dist-info/METADATA
gmlp_flax-0.0.1.dist-info/WHEEL
gmlp_flax-0.0.1.dist-info/top_level.txt
gmlp_flax-0.0.1.dist-info/zip-safe
gmlp_flax-0.0.1.dist-info/RECORD
