Metadata-Version: 2.1
Name: gmlp-flax
Version: 0.0.1
Summary: Flax implementation of gMLP from Pay Attention to MLPs
Home-page: https://github.com/SauravMaheshkar/gMLP
Author: Saurav Maheshkar
Author-email: sauravvmaheshkar@gmail.com
License: MIT
Platform: UNKNOWN
Requires-Dist: einops (>=0.3)
Requires-Dist: flax
Requires-Dist: jax
